Metadata-Version: 2.1
Name: slytherin
Version: 2020.9.18.2
Summary: Python library of useful but lonely functions and classes
Home-page: https://github.com/idin/slytherin
Author: Idin
Author-email: py@idin.ca
License: MIT
Platform: UNKNOWN
Requires-Python: ~=3.6
Requires-Dist: base32hex
Requires-Dist: geopy
